typed_ast-stubs/METADATA.toml
typed_ast-stubs/__init__.pyi
typed_ast-stubs/ast27.pyi
typed_ast-stubs/ast3.pyi
typed_ast-stubs/conversions.pyi
types_typed_ast-1.5.8.6.dist-info/METADATA
types_typed_ast-1.5.8.6.dist-info/WHEEL
types_typed_ast-1.5.8.6.dist-info/top_level.txt
types_typed_ast-1.5.8.6.dist-info/RECORD
