Metadata-Version: 2.1
Name: types-typed-ast
Version: 1.5.8.6
Summary: Typing stubs for typed-ast
Home-page: https://github.com/python/typeshed
License: Apache-2.0 license
Project-URL: GitHub, https://github.com/python/typeshed
Project-URL: Changes, https://github.com/typeshed-internal/stub_uploader/blob/main/data/changelogs/typed-ast.md
Project-URL: Issue tracker, https://github.com/python/typeshed/issues
Project-URL: Chat, https://gitter.im/python/typing
Classifier: License :: OSI Approved :: Apache Software License
Classifier: Programming Language :: Python :: 3
Classifier: Typing :: Stubs Only
